README.md
setup.cfg
setup.py
tpes/__init__.py
tpes/__main__.py
tpes/command_class_inspection.py
tpes/command_executor.py
tpes/environment.py
tpes/expression.py
tpes/formatters.py
tpes/instance_management.py
tpes/instance_parser.py
tpes/workflow_parser.py
tpes.egg-info/PKG-INFO
tpes.egg-info/SOURCES.txt
tpes.egg-info/dependency_links.txt
tpes.egg-info/entry_points.txt
tpes.egg-info/requires.txt
tpes.egg-info/top_level.txt
tpes/data/__init__.py
tpes/data/connection.py
tpes/data/data_objects.py
tpes/data/instance.py
tpes/data/node.py
tpes/data/workflow.py
tpes/todo/__init__.py
tpes/todo/base.py
tpes/todo/formats.py
tpes/tui/__init__.py
tpes/tui/__main__.py
tpes/ui/__init__.py
tpes/views/__init__.py
tpes/views/items.py
tpes/views/workflow_details.py